{"name":"Batalla de Milk Creek","parent":"Guerra ute de 1879","type":"batalla","scope":"regional","region":"Colorado","cause":"Tensiones por tierras, agencias y presencia militar estadounidense derivaron en combate con los ute.","chronology":[{"year":1879,"text":"Combate dentro de Guerra ute de 1879."}],"related":["Guerra ute de 1879"],"participants":[{"side":"Estados Unidos","members":["Estados Unidos"],"organizations":[],"troops":"fuerzas variables","casualties":"inciertas"},{"side":"Ute","members":["Ute"],"organizations":[],"troops":"fuerzas variables","casualties":"inciertas"}],"outcome":"Resistencia ute frente a una columna estadounidense.","consequences":"Aumento la presion federal y acelero el desplazamiento forzado de comunidades ute.","source":"Curaduria GeoRisk","pageTitle":"Batalla de Milk Creek","war":"Guerra ute de 1879","campaign":"Campana vinculada a Guerra ute de 1879","conflictType":"interestatal","scale":"local","status":"historico","active":false,"normalizedRegion":"Colorado","treaties":[],"curationPriority":"alta","curationBatch":"safe-structured-conflict-curation-2026-06","curationNote":"Metadatos estructurales agregados por tanda segura; bajas y tratados especificos quedan como no consolidados si no habia fuente fina.","curationStatus":"estructural","dataConfidence":"parcial"}
