{"name":"Batalla de Ibiza","parent":"Guerra de Independencia de Estados Unidos","type":"batalla naval","scope":"regional","region":"Mediterráneo occidental","cause":"La guerra naval global afecto convoyes, corsarios y rutas comerciales europeas.","chronology":[{"year":1780,"text":"Combate dentro de Guerra de Independencia de Estados Unidos."}],"related":["Guerra de Independencia de Estados Unidos"],"participants":[{"side":"Reino Unido","members":["Reino Unido"],"organizations":[],"troops":"fuerzas variables","casualties":"inciertas"},{"side":"Espana y aliados","members":["España"],"organizations":[],"troops":"fuerzas variables","casualties":"inciertas"}],"outcome":"Acción naval vinculada a la guerra maritima global.","consequences":"Reflejo como la independencia estadounidense se conecto con rivalidades europeas mas amplias.","source":"Curaduria GeoRisk","pageTitle":"Batalla de Ibiza","war":"Guerra de Independencia de Estados Unidos","campaign":"Campaña vinculada a Guerra de Independencia de Estados Unidos","conflictType":"independencia","scale":"local","status":"historico","active":false,"normalizedRegion":"Mediterráneo occidental","treaties":[],"curationPriority":"alta","curationBatch":"safe-structured-conflict-curation-2026-06","curationNote":"Metadatos estructurales agregados por tanda segura; bajas y tratados específicos quedan como no consolidados si no había fuente fina.","curationStatus":"estructural","dataConfidence":"parcial","ongoing":false}
