{"name":"Batalla de Big Hole","parent":"Guerra de los Nez Perce","war":"Guerra de los Nez Perce","campaign":"Huida de los Nez Perce de 1877","type":"batalla","conflictType":"colonial","scale":"local","status":"historico","active":false,"ongoing":false,"startYear":1877,"endYear":1877,"region":"Valle de Big Hole, Montana, Estados Unidos","normalizedRegion":"Valle de Big Hole, Montana, Estados Unidos","cause":"La orden de trasladar a los grupos nimiipuu que vivían fuera de la reserva de 1863 desencadenó la huida y los combates de 1877.","outcome":"El ataque estadounidense causó numerosas bajas, pero los nimiipuu rompieron el cerco y continuaron la marcha.","consequences":"La acción condicionó la marcha de más de mil kilómetros de los nimiipuu en busca de refugio antes de Bear Paw.","chronology":[{"year":1877,"event":"El ataque estadounidense causó numerosas bajas, pero los nimiipuu rompieron el cerco y continuaron la marcha."}],"treaties":[],"related":["Guerra de los Nez Perce","Huida de los Nez Perce de 1877"],"participants":[{"side":"Estados Unidos","members":["Estados Unidos"]},{"side":"Nimiipuu (Nez Perce)","members":["Nez Perce"]}],"hierarchyConfidence":"alta","hierarchySources":[{"label":"Servicio de Parques Nacionales de EE. UU.: ruta y batallas de los Nez Perce de 1877","url":"https://www.nps.gov/biho/planyourvisit/park-brochure.htm"}],"curationPriority":"alta","curationBatch":"source-backed-us-indian-wars-followup-2026-07","curationStatus":"estructural","dataConfidence":"parcial","source":"Curaduria GeoRisk","pageTitle":"Batalla de Big Hole","curationNote":"Metadatos estructurales agregados por tanda segura; bajas, tratados y resultados finos no se inventan si no había fuente específica."}
