{"name":"Batalla de Cuddalore (1758)","parent":"Guerra de los Siete Anos","type":"batalla","scope":"regional","region":"India","cause":"Competencia franco-britanica por enclaves comerciales y poder regional en el subcontinente indio.","chronology":[{"year":1758,"text":"Combate dentro de Guerra de los Siete Anos."}],"related":["Guerra de los Siete Anos"],"participants":[{"side":"Francia y aliados locales","members":["Francia"],"organizations":[],"troops":"fuerzas variables","casualties":"inciertas"},{"side":"Reino Unido y aliados locales","members":["Reino Unido"],"organizations":[],"troops":"fuerzas variables","casualties":"inciertas"}],"outcome":"Episodio tactico de la guerra colonial en India.","consequences":"Se integro en la rivalidad global franco-britanica que redefinio el equilibrio colonial.","source":"Curaduria GeoRisk","pageTitle":"Batalla de Cuddalore (1758)"}
