{"name":"Batalla de Las Guasimas (1898)","parent":"Guerra hispano-estadounidense","type":"batalla","scope":"regional","region":"Cuba","cause":"Fuerzas estadounidenses avanzaron hacia Santiago de Cuba contra defensas espanolas.","chronology":[{"year":1898,"text":"Combate dentro de Guerra hispano-estadounidense."}],"related":["Guerra hispano-estadounidense"],"participants":[{"side":"Estados Unidos","members":["Estados Unidos"],"organizations":[],"troops":"fuerzas variables","casualties":"inciertas"},{"side":"España","members":["España"],"organizations":[],"troops":"fuerzas variables","casualties":"inciertas"}],"outcome":"Victoria estadounidense táctica.","consequences":"Abrio el camino hacia combates mayores en San Juan y Santiago.","source":"Curaduria GeoRisk","pageTitle":"Batalla de Las Guasimas (1898)","war":"Guerra hispano-estadounidense","campaign":"Campaña vinculada a Guerra hispano-estadounidense","conflictType":"interestatal","scale":"internacional","status":"historico","active":false,"normalizedRegion":"Cuba","treaties":["Cierre o arreglo posterior pendiente de curaduría específica (1898)"],"curationPriority":"alta","curationBatch":"safe-structured-conflict-curation-2026-06","curationNote":"Metadatos estructurales agregados por tanda segura; bajas y tratados especificos quedan como no consolidados si no había fuente fina.","curationStatus":"estructural","dataConfidence":"parcial"}
